RTL/Reset_Synchronizer/RST_SYNC.v
module RST_SYNC #(parameter NUM_STAGES = 2)(
    input wire  RST,
    input wire  CLK,
    output wire SYNC_RST
);
    reg [NUM_STAGES-1:0] sync_ff;
    integer i;

    assign SYNC_RST = sync_ff[NUM_STAGES-1];

    always @(posedge CLK or negedge RST) begin
        if (!RST) begin
            sync_ff <= 'b0;
        end else begin
            sync_ff[0] <= 1'b1;
            for (i=1 ; i<NUM_STAGES ; i=i+1) begin
                sync_ff[i] <= sync_ff[i-1];
            end
        end
    end
endmodule

RTL/Reset_Synchronizer/RST_SYNC_tb.v
`timescale 1ns / 1ps
module RST_SYNC_tb ();
    // Testbench signals
    reg RST_tb;
    reg CLK_tb;
    wire SYNC_RST_tb;

    parameter CLOCK_PERIOD = 10;
    parameter NUM_STAGES = 6;

    // CLK Generator
    always #(CLOCK_PERIOD/2) CLK_tb = ~CLK_tb;

    // Design Instantiation
    RST_SYNC #(.NUM_STAGES(NUM_STAGES)) DUT(
        .RST(RST_tb),
        .CLK(CLK_tb),
        .SYNC_RST(SYNC_RST_tb)
    );

    initial begin
        $dumpfile("RST_SYNC.vcd");           // Save waveform to this file     
        $dumpvars;                           // Dump all variables recursively 

        initialize;
        reset;

        #(10*CLOCK_PERIOD)

        $stop;
    end


    // Tasks Definitions 
    task initialize;
    begin
        CLK_tb = 1'b0;
    end
    endtask

    task reset;
    begin
        RST_tb = 1'b1;
        #((NUM_STAGES+1)*CLOCK_PERIOD)
        RST_tb = 1'b0;
        #(CLOCK_PERIOD)
        RST_tb = 1'b1;
    end
    endtask

endmodule

RTL/Reset_Synchronizer/RST_SYNC.vcd
$date
	Mon Sep  1 15:19:21 2025
$end
$version
	QuestaSim Version 2021.1
$end
$timescale
	1ps
$end

$scope module RST_SYNC_tb $end
$var parameter 32 ! CLOCK_PERIOD $end
$var parameter 32 " NUM_STAGES $end
$var reg 1 # RST_tb $end
$var reg 1 $ CLK_tb $end
$var wire 1 % SYNC_RST_tb $end

$scope task initialize $end
$upscope $end

$scope task reset $end
$upscope $end

$scope module DUT $end
$var parameter 32 & NUM_STAGES $end
$var wire 1 ' RST $end
$var wire 1 ( CLK $end
$var reg 1 ) SYNC_RST $end
$var reg 6 * sync_ff [5:0] $end
$var integer 32 + i $end
$upscope $end
$upscope $end
$enddefinitions $end
#0
$dumpvars
1#
0$
x)
bx *
b1010 !
b110 "
b110 &
bx +
x%
0(
1'
$end
#5000
1$
1(
b1 +
b10 +
b11 +
b100 +
b101 +
b110 +
bx1 *
#10000
0$
0(
#15000
1$
1(
b1 +
b10 +
b11 +
b100 +
b101 +
b110 +
bx11 *
#20000
0$
0(
#25000
1$
1(
b1 +
b10 +
b11 +
b100 +
b101 +
b110 +
bx111 *
#30000
0$
0(
#35000
1$
1(
b1 +
b10 +
b11 +
b100 +
b101 +
b110 +
bx1111 *
#40000
0$
0(
#45000
1$
1(
b1 +
b10 +
b11 +
b100 +
b101 +
b110 +
bx11111 *
#50000
0$
0(
#55000
1$
1(
b1 +
b10 +
b11 +
b100 +
b101 +
b110 +
b111111 *
#60000
0$
0(
#65000
1$
1(
b1 +
b10 +
b11 +
b100 +
b101 +
b110 +
1)
1%
#70000
0#
0$
0'
0(
0)
b0 *
0%
#75000
1$
1(
#80000
1#
0$
1'
0(
#85000
1$
1(
b1 +
b10 +
b11 +
b100 +
b101 +
b110 +
b1 *
#90000
0$
0(
#95000
1$
1(
b1 +
b10 +
b11 +
b100 +
b101 +
b110 +
b11 *
#100000
0$
0(
#105000
1$
1(
b1 +
b10 +
b11 +
b100 +
b101 +
b110 +
b111 *
#110000
0$
0(
#115000
1$
1(
b1 +
b10 +
b11 +
b100 +
b101 +
b110 +
b1111 *
#120000
0$
0(
#125000
1$
1(
b1 +
b10 +
b11 +
b100 +
b101 +
b110 +
b11111 *
#130000
0$
0(
#135000
1$
1(
b1 +
b10 +
b11 +
b100 +
b101 +
b110 +
b111111 *
#140000
0$
0(
#145000
1$
1(
b1 +
b10 +
b11 +
b100 +
b101 +
b110 +
1)
1%
#150000
0$
0(
#155000
1$
1(
b1 +
b10 +
b11 +
b100 +
b101 +
b110 +
