RTL/Clock_Divider/Clock_Divider.v
module Clock_Divider #( 
    parameter RATIO_WD = 8 
)
(
    input wire       i_ref_clk,
    input wire       i_rst_n,
    input wire       i_clk_en,
    input wire [RATIO_WD-1:0] i_div_ratio,
    output wire      o_div_clk
);
    reg [RATIO_WD-1:0] counter;
    wire div_odd;
    wire [RATIO_WD-1:0] high_pulse;
    wire [RATIO_WD-1:0] low_pulse;
    reg div_clk;
    reg flag;
    wire clk_en;
    wire high_condition;
    wire low_condition;

    assign clk_en = i_clk_en && (i_div_ratio != 'd1) && (i_div_ratio != 'd0);
    assign div_odd = i_div_ratio[0];
    assign high_pulse = i_div_ratio >> 1;
    assign low_pulse = i_div_ratio - high_pulse;
    assign high_condition = (counter == high_pulse - 1) && flag;
    assign low_condition = (counter == low_pulse - 1) && !flag;
    assign o_div_clk = clk_en ? div_clk : i_ref_clk;

    always @(posedge i_ref_clk or negedge i_rst_n) begin
        if (!i_rst_n) begin
            div_clk <= 1'b0;
            counter <= 'd0;
            flag <= 1'b0;
        end else if (clk_en && !div_odd && (counter == (high_pulse - 1))) begin
            div_clk <= ~div_clk;
            counter <= 'd0;
        end else if (clk_en && div_odd && ((high_condition) || (low_condition))) begin
            div_clk <= ~div_clk;
            counter <= 'd0;
            flag <= ~flag;                  // flag = 1 when div_vlk = 1 
                                            // flag = 0 when div_vlk = 0 
        end else if(clk_en) begin
            counter <= counter + 1'd1;
        end else begin
            counter <= 'd0;
        end
    end

endmodule

RTL/Clock_Divider/Clock_Divider_tb.v
`timescale 1ns / 1ps
module Clock_Divider_tb();
// Testbench signals
reg       i_ref_clk_tb;
reg       i_rst_n_tb;
reg       i_clk_en_tb;
reg [7:0] i_div_ratio_tb;
wire      o_div_clk_tb;

parameter CLOCK_REF_PERIOD = 10;

// ref_clk Generator
always #(CLOCK_REF_PERIOD/2) i_ref_clk_tb = ~i_ref_clk_tb;

// Design Instantiation
Clock_Divider DUT (
    .i_ref_clk(i_ref_clk_tb),
    .i_rst_n(i_rst_n_tb),
    .i_clk_en(i_clk_en_tb),
    .i_div_ratio(i_div_ratio_tb),
    .o_div_clk(o_div_clk_tb)
);

initial begin
    $dumpfile("Clock_Divider.vcd");           // Save waveform to this file     
    $dumpvars;                                // Dump all variables recursively 

    initialize;
    reset;

    // === Test Case 1: clk_en = 1, div_ratio = 0 ===
    in(1,0);
    #(10*CLOCK_REF_PERIOD);

    // === Test Case 2: clk_en = 1, div_ratio = 1 ===
    in(1,1);
    #(10*CLOCK_REF_PERIOD);

    // === Test Case 3: clk_en = 1, div_ratio = 2 ===
    in(1,2);
    #(20*CLOCK_REF_PERIOD);

    // === Test Case 4: clk_en = 1, div_ratio = 3 ===
    in(1,3);
    #(20*CLOCK_REF_PERIOD);

    // === Test Case 5: clk_en = 1, div_ratio = 4 ===
    in(1,4);
    #(20*CLOCK_REF_PERIOD);

    // === Test Case 6: clk_en = 1, div_ratio = 5 ===
    in(1,5);
    #(20*CLOCK_REF_PERIOD);

    // === Test Case 7: clk_en = 1, div_ratio = 6 ===
    in(1,6);
    #(20*CLOCK_REF_PERIOD);

    // === Test Case 8: clk_en = 1, div_ratio = 7 ===
    in(1,7);
    #(30*CLOCK_REF_PERIOD);

    // === Test Case 9: clk_en = 0, div_ratio = 2 ===
    in(0,2);
    #(20*CLOCK_REF_PERIOD);

    // === Test Case 10: clk_en = 1, div_ratio = 5 ===
    in(1,5);
    #(20*CLOCK_REF_PERIOD);

    // === Test Case 11: clk_en = 1, div_ratio = 4 ===
    in(1,4);
    #(20*CLOCK_REF_PERIOD);
    $stop;
end

// Tasks Definitions 
    task initialize;
    begin
        i_ref_clk_tb = 1'b0;
        i_clk_en_tb = 1'b0;
        i_div_ratio_tb = 8'b0;
    end
    endtask

    task reset;
    begin
        i_rst_n_tb = 1'b1;
        #(CLOCK_REF_PERIOD)
        i_rst_n_tb = 1'b0;
        #(CLOCK_REF_PERIOD)
        i_rst_n_tb = 1'b1;
    end
    endtask

    task in(input enable, input [7:0] div_ratio);
    begin
        i_clk_en_tb = enable;
        i_div_ratio_tb = div_ratio;
    end
    endtask
endmodule

RTL/Clock_Divider/Clock_Divider.vcd
$date
	Thu Aug 28 13:09:55 2025
$end
$version
	QuestaSim Version 2021.1
$end
$timescale
	1ps
$end

$scope module Clock_Divider_tb $end
$var parameter 32 ! CLOCK_REF_PERIOD $end
$var reg 1 " i_ref_clk_tb $end
$var reg 1 # i_rst_n_tb $end
$var reg 1 $ i_clk_en_tb $end
$var reg 8 % i_div_ratio_tb [7:0] $end
$var wire 1 & o_div_clk_tb $end

$scope task initialize $end
$upscope $end

$scope task reset $end
$upscope $end

$scope task in $end
$var reg 1 ' enable $end
$var reg 8 ( div_ratio [7:0] $end
$upscope $end

$scope module DUT $end
$var wire 1 ) i_ref_clk $end
$var wire 1 * i_rst_n $end
$var wire 1 + i_clk_en $end
$var wire 1 , i_div_ratio [7] $end
$var wire 1 - i_div_ratio [6] $end
$var wire 1 . i_div_ratio [5] $end
$var wire 1 / i_div_ratio [4] $end
$var wire 1 0 i_div_ratio [3] $end
$var wire 1 1 i_div_ratio [2] $end
$var wire 1 2 i_div_ratio [1] $end
$var wire 1 3 i_div_ratio [0] $end
$var wire 1 & o_div_clk $end
$var reg 8 4 counter [7:0] $end
$var wire 1 5 div_odd $end
$var wire 1 6 high_pulse [7] $end
$var wire 1 7 high_pulse [6] $end
$var wire 1 8 high_pulse [5] $end
$var wire 1 9 high_pulse [4] $end
$var wire 1 : high_pulse [3] $end
$var wire 1 ; high_pulse [2] $end
$var wire 1 < high_pulse [1] $end
$var wire 1 = high_pulse [0] $end
$var wire 1 > low_pulse [7] $end
$var wire 1 ? low_pulse [6] $end
$var wire 1 @ low_pulse [5] $end
$var wire 1 A low_pulse [4] $end
$var wire 1 B low_pulse [3] $end
$var wire 1 C low_pulse [2] $end
$var wire 1 D low_pulse [1] $end
$var wire 1 E low_pulse [0] $end
$var reg 1 F div_clk $end
$var reg 1 G flag $end
$var wire 1 H clk_en $end
$var wire 1 I high_condition $end
$var wire 1 J low_condition $end
$upscope $end
$upscope $end
$enddefinitions $end
#0
$dumpvars
0"
1#
0$
b0 %
bx 4
xF
xG
x'
bx (
b1010 !
0&
05
0=
0<
0;
0:
09
08
07
06
0E
0D
0C
0B
0A
0@
0?
0>
0H
0I
0J
03
02
01
00
0/
0.
0-
0,
0+
1*
0)
$end
#5000
1"
1)
1&
b0 4
#10000
0#
0"
0*
0)
0&
0F
0G
#15000
1"
1)
1&
#20000
1#
1'
b0 (
1$
0"
1+
1*
0)
0&
#25000
1"
1)
1&
#30000
0"
0)
0&
#35000
1"
1)
1&
#40000
0"
0)
0&
#45000
1"
1)
1&
#50000
0"
0)
0&
#55000
1"
1)
1&
#60000
0"
0)
0&
#65000
1"
1)
1&
#70000
0"
0)
0&
#75000
1"
1)
1&
#80000
0"
0)
0&
#85000
1"
1)
1&
#90000
0"
0)
0&
#95000
1"
1)
1&
#100000
0"
0)
0&
#105000
1"
1)
1&
#110000
0"
0)
0&
#115000
1"
1)
1&
#120000
b1 (
b1 %
0"
13
15
1E
1J
0)
0&
#125000
1"
1)
1&
#130000
0"
0)
0&
#135000
1"
1)
1&
#140000
0"
0)
0&
#145000
1"
1)
1&
#150000
0"
0)
0&
#155000
1"
1)
1&
#160000
0"
0)
0&
#165000
1"
1)
1&
#170000
0"
0)
0&
#175000
1"
1)
1&
#180000
0"
0)
0&
#185000
1"
1)
1&
#190000
0"
0)
0&
#195000
1"
1)
1&
#200000
0"
0)
0&
#205000
1"
1)
1&
#210000
0"
0)
0&
#215000
1"
1)
1&
#220000
b10 (
b10 %
0"
03
12
05
1=
0E
1D
1H
0&
0J
1E
0D
1J
0)
#225000
1"
1)
1F
1&
#230000
0"
0)
#235000
1"
1)
0F
0&
#240000
0"
0)
#245000
1"
1)
1F
1&
#250000
0"
0)
#255000
1"
1)
0F
0&
#260000
0"
0)
#265000
1"
1)
1F
1&
#270000
0"
0)
#275000
1"
1)
0F
0&
#280000
0"
0)
#285000
1"
1)
1F
1&
#290000
0"
0)
#295000
1"
1)
0F
0&
#300000
0"
0)
#305000
1"
1)
1F
1&
#310000
0"
0)
#315000
1"
1)
0F
0&
#320000
0"
0)
#325000
1"
1)
1F
1&
#330000
0"
0)
#335000
1"
1)
0F
0&
#340000
0"
0)
#345000
1"
1)
1F
1&
#350000
0"
0)
#355000
1"
1)
0F
0&
#360000
0"
0)
#365000
1"
1)
1F
1&
#370000
0"
0)
#375000
1"
1)
0F
0&
#380000
0"
0)
#385000
1"
1)
1F
1&
#390000
0"
0)
#395000
1"
1)
0F
0&
#400000
0"
0)
#405000
1"
1)
1F
1&
#410000
0"
0)
#415000
1"
1)
0F
0&
#420000
b11 (
b11 %
0"
13
15
0E
1D
0J
0)
#425000
1"
1)
b1 4
1J
#430000
0"
0)
#435000
1"
1)
1F
b0 4
1G
1&
0J
1I
#440000
0"
0)
#445000
1"
1)
0F
0G
0&
0I
#450000
0"
0)
#455000
1"
1)
b1 4
1J
#460000
0"
0)
#465000
1"
1)
1F
b0 4
1G
1&
0J
1I
#470000
0"
0)
#475000
1"
1)
0F
0G
0&
0I
#480000
0"
0)
#485000
1"
1)
b1 4
1J
#490000
0"
0)
#495000
1"
1)
1F
b0 4
1G
1&
0J
1I
#500000
0"
0)
#505000
1"
1)
0F
0G
0&
0I
#510000
0"
0)
#515000
1"
1)
b1 4
1J
#520000
0"
0)
#525000
1"
1)
1F
b0 4
1G
1&
0J
1I
#530000
0"
0)
#535000
1"
1)
0F
0G
0&
0I
#540000
0"
0)
#545000
1"
1)
b1 4
1J
#550000
0"
0)
#555000
1"
1)
1F
b0 4
1G
1&
0J
1I
#560000
0"
0)
#565000
1"
1)
0F
0G
0&
0I
#570000
0"
0)
#575000
1"
1)
b1 4
1J
#580000
0"
0)
#585000
1"
1)
1F
b0 4
1G
1&
0J
1I
#590000
0"
0)
#595000
1"
1)
0F
0G
0&
0I
#600000
0"
0)
#605000
1"
1)
b1 4
1J
#610000
0"
0)
#615000
1"
1)
1F
b0 4
1G
1&
0J
1I
#620000
b100 (
b100 %
0"
03
02
11
05
0=
1<
1E
0I
0E
0)
#625000
1"
1)
b1 4
1I
#630000
0"
0)
#635000
1"
1)
0F
b0 4
0&
0I
#640000
0"
0)
#645000
1"
1)
b1 4
1I
#650000
0"
0)
#655000
1"
1)
1F
b0 4
1&
0I
#660000
0"
0)
#665000
1"
1)
b1 4
1I
#670000
0"
0)
#675000
1"
1)
0F
b0 4
0&
0I
#680000
0"
0)
#685000
1"
1)
b1 4
1I
#690000
0"
0)
#695000
1"
1)
1F
b0 4
1&
0I
#700000
0"
0)
#705000
1"
1)
b1 4
1I
#710000
0"
0)
#715000
1"
1)
0F
b0 4
0&
0I
#720000
0"
0)
#725000
1"
1)
b1 4
1I
#730000
0"
0)
#735000
1"
1)
1F
b0 4
1&
0I
#740000
0"
0)
#745000
1"
1)
b1 4
1I
#750000
0"
0)
#755000
1"
1)
0F
b0 4
0&
0I
#760000
0"
0)
#765000
1"
1)
b1 4
1I
#770000
0"
0)
#775000
1"
1)
1F
b0 4
1&
0I
#780000
0"
0)
#785000
1"
1)
b1 4
1I
#790000
0"
0)
#795000
1"
1)
0F
b0 4
0&
0I
#800000
0"
0)
#805000
1"
1)
b1 4
1I
#810000
0"
0)
#815000
1"
1)
1F
b0 4
1&
0I
#820000
b101 (
b101 %
0"
13
15
1E
0)
#825000
1"
1)
b1 4
1I
#830000
0"
0)
#835000
1"
1)
0F
b0 4
0G
0&
0I
#840000
0"
0)
#845000
1"
1)
b1 4
#850000
0"
0)
#855000
1"
1)
b10 4
1J
#860000
0"
0)
#865000
1"
1)
1F
b0 4
1G
1&
0J
#870000
0"
0)
#875000
1"
1)
b1 4
1I
#880000
0"
0)
#885000
1"
1)
0F
b0 4
0G
0&
0I
#890000
0"
0)
#895000
1"
1)
b1 4
#900000
0"
0)
#905000
1"
1)
b10 4
1J
#910000
0"
0)
#915000
1"
1)
1F
b0 4
1G
1&
0J
#920000
0"
0)
#925000
1"
1)
b1 4
1I
#930000
0"
0)
#935000
1"
1)
0F
b0 4
0G
0&
0I
#940000
0"
0)
#945000
1"
1)
b1 4
#950000
0"
0)
#955000
1"
1)
b10 4
1J
#960000
0"
0)
#965000
1"
1)
1F
b0 4
1G
1&
0J
#970000
0"
0)
#975000
1"
1)
b1 4
1I
#980000
0"
0)
#985000
1"
1)
0F
b0 4
0G
0&
0I
#990000
0"
0)
#995000
1"
1)
b1 4
#1000000
0"
0)
#1005000
1"
1)
b10 4
1J
#1010000
0"
0)
#1015000
1"
1)
1F
b0 4
1G
1&
0J
#1020000
b110 (
b110 %
0"
03
12
05
1=
0E
0D
1C
1E
1D
0C
0)
#1025000
1"
1)
b1 4
#1030000
0"
0)
#1035000
1"
1)
b10 4
1I
#1040000
0"
0)
#1045000
1"
1)
0F
b0 4
0&
0I
#1050000
0"
0)
#1055000
1"
1)
b1 4
#1060000
0"
0)
#1065000
1"
1)
b10 4
1I
#1070000
0"
0)
#1075000
1"
1)
1F
b0 4
1&
0I
#1080000
0"
0)
#1085000
1"
1)
b1 4
#1090000
0"
0)
#1095000
1"
1)
b10 4
1I
#1100000
0"
0)
#1105000
1"
1)
0F
b0 4
0&
0I
#1110000
0"
0)
#1115000
1"
1)
b1 4
#1120000
0"
0)
#1125000
1"
1)
b10 4
1I
#1130000
0"
0)
#1135000
1"
1)
1F
b0 4
1&
0I
#1140000
0"
0)
#1145000
1"
1)
b1 4
#1150000
0"
0)
#1155000
1"
1)
b10 4
1I
#1160000
0"
0)
#1165000
1"
1)
0F
b0 4
0&
0I
#1170000
0"
0)
#1175000
1"
1)
b1 4
#1180000
0"
0)
#1185000
1"
1)
b10 4
1I
#1190000
0"
0)
#1195000
1"
1)
1F
b0 4
1&
0I
#1200000
0"
0)
#1205000
1"
1)
b1 4
#1210000
0"
0)
#1215000
1"
1)
b10 4
1I
#1220000
b111 (
b111 %
0"
13
15
0E
0D
1C
0)
#1225000
1"
1)
0F
b0 4
0G
0&
0I
#1230000
0"
0)
#1235000
1"
1)
b1 4
#1240000
0"
0)
#1245000
1"
1)
b10 4
#1250000
0"
0)
#1255000
1"
1)
b11 4
1J
#1260000
0"
0)
#1265000
1"
1)
1F
b0 4
1G
1&
0J
#1270000
0"
0)
#1275000
1"
1)
b1 4
#1280000
0"
0)
#1285000
1"
1)
b10 4
1I
#1290000
0"
0)
#1295000
1"
1)
0F
b0 4
0G
0&
0I
#1300000
0"
0)
#1305000
1"
1)
b1 4
#1310000
0"
0)
#1315000
1"
1)
b10 4
#1320000
0"
0)
#1325000
1"
1)
b11 4
1J
#1330000
0"
0)
#1335000
1"
1)
1F
b0 4
1G
1&
0J
#1340000
0"
0)
#1345000
1"
1)
b1 4
#1350000
0"
0)
#1355000
1"
1)
b10 4
1I
#1360000
0"
0)
#1365000
1"
1)
0F
b0 4
0G
0&
0I
#1370000
0"
0)
#1375000
1"
1)
b1 4
#1380000
0"
0)
#1385000
1"
1)
b10 4
#1390000
0"
0)
#1395000
1"
1)
b11 4
1J
#1400000
0"
0)
#1405000
1"
1)
1F
b0 4
1G
1&
0J
#1410000
0"
0)
#1415000
1"
1)
b1 4
#1420000
0"
0)
#1425000
1"
1)
b10 4
1I
#1430000
0"
0)
#1435000
1"
1)
0F
b0 4
0G
0&
0I
#1440000
0"
0)
#1445000
1"
1)
b1 4
#1450000
0"
0)
#1455000
1"
1)
b10 4
#1460000
0"
0)
#1465000
1"
1)
b11 4
1J
#1470000
0"
0)
#1475000
1"
1)
1F
b0 4
1G
1&
0J
#1480000
0"
0)
#1485000
1"
1)
b1 4
#1490000
0"
0)
#1495000
1"
1)
b10 4
1I
#1500000
0"
0)
#1505000
1"
1)
0F
b0 4
0G
0&
0I
#1510000
0"
0)
#1515000
1"
1)
b1 4
#1520000
0'
b10 (
0$
b10 %
0"
0+
03
01
05
0H
0<
1E
1D
1B
1A
1@
1?
1>
1&
0D
0C
0B
0A
0@
0?
0>
0)
0&
#1525000
1"
1)
1&
b0 4
1J
#1530000
0"
0)
0&
#1535000
1"
1)
1&
#1540000
0"
0)
0&
#1545000
1"
1)
1&
#1550000
0"
0)
0&
#1555000
1"
1)
1&
#1560000
0"
0)
0&
#1565000
1"
1)
1&
#1570000
0"
0)
0&
#1575000
1"
1)
1&
#1580000
0"
0)
0&
#1585000
1"
1)
1&
#1590000
0"
0)
0&
#1595000
1"
1)
1&
#1600000
0"
0)
0&
#1605000
1"
1)
1&
#1610000
0"
0)
0&
#1615000
1"
1)
1&
#1620000
0"
0)
0&
#1625000
1"
1)
1&
#1630000
0"
0)
0&
#1635000
1"
1)
1&
#1640000
0"
0)
0&
#1645000
1"
1)
1&
#1650000
0"
0)
0&
#1655000
1"
1)
1&
#1660000
0"
0)
0&
#1665000
1"
1)
1&
#1670000
0"
0)
0&
#1675000
1"
1)
1&
#1680000
0"
0)
0&
#1685000
1"
1)
1&
#1690000
0"
0)
0&
#1695000
1"
1)
1&
#1700000
0"
0)
0&
#1705000
1"
1)
1&
#1710000
0"
0)
0&
#1715000
1"
1)
1&
#1720000
1'
b101 (
1$
b101 %
0"
1+
13
02
11
15
1H
0=
1<
0E
1C
0&
0J
1E
1D
0C
0)
#1725000
1"
1)
b1 4
#1730000
0"
0)
#1735000
1"
1)
b10 4
1J
#1740000
0"
0)
#1745000
1"
1)
1F
b0 4
1G
1&
0J
#1750000
0"
0)
#1755000
1"
1)
b1 4
1I
#1760000
0"
0)
#1765000
1"
1)
0F
b0 4
0G
0&
0I
#1770000
0"
0)
#1775000
1"
1)
b1 4
#1780000
0"
0)
#1785000
1"
1)
b10 4
1J
#1790000
0"
0)
#1795000
1"
1)
1F
b0 4
1G
1&
0J
#1800000
0"
0)
#1805000
1"
1)
b1 4
1I
#1810000
0"
0)
#1815000
1"
1)
0F
b0 4
0G
0&
0I
#1820000
0"
0)
#1825000
1"
1)
b1 4
#1830000
0"
0)
#1835000
1"
1)
b10 4
1J
#1840000
0"
0)
#1845000
1"
1)
1F
b0 4
1G
1&
0J
#1850000
0"
0)
#1855000
1"
1)
b1 4
1I
#1860000
0"
0)
#1865000
1"
1)
0F
b0 4
0G
0&
0I
#1870000
0"
0)
#1875000
1"
1)
b1 4
#1880000
0"
0)
#1885000
1"
1)
b10 4
1J
#1890000
0"
0)
#1895000
1"
1)
1F
b0 4
1G
1&
0J
#1900000
0"
0)
#1905000
1"
1)
b1 4
1I
#1910000
0"
0)
#1915000
1"
1)
0F
b0 4
0G
0&
0I
#1920000
b100 (
b100 %
0"
03
05
0E
0)
#1925000
1"
1)
b1 4
1J
#1930000
0"
0)
#1935000
1"
1)
1F
b0 4
1&
0J
#1940000
0"
0)
#1945000
1"
1)
b1 4
1J
#1950000
0"
0)
#1955000
1"
1)
0F
b0 4
0&
0J
#1960000
0"
0)
#1965000
1"
1)
b1 4
1J
#1970000
0"
0)
#1975000
1"
1)
1F
b0 4
1&
0J
#1980000
0"
0)
#1985000
1"
1)
b1 4
1J
#1990000
0"
0)
#1995000
1"
1)
0F
b0 4
0&
0J
#2000000
0"
0)
#2005000
1"
1)
b1 4
1J
#2010000
0"
0)
#2015000
1"
1)
1F
b0 4
1&
0J
#2020000
0"
0)
#2025000
1"
1)
b1 4
1J
#2030000
0"
0)
#2035000
1"
1)
0F
b0 4
0&
0J
#2040000
0"
0)
#2045000
1"
1)
b1 4
1J
#2050000
0"
0)
#2055000
1"
1)
1F
b0 4
1&
0J
#2060000
0"
0)
#2065000
1"
1)
b1 4
1J
#2070000
0"
0)
#2075000
1"
1)
0F
b0 4
0&
0J
#2080000
0"
0)
#2085000
1"
1)
b1 4
1J
#2090000
0"
0)
#2095000
1"
1)
1F
b0 4
1&
0J
#2100000
0"
0)
#2105000
1"
1)
b1 4
1J
#2110000
0"
0)
#2115000
1"
1)
0F
b0 4
0&
0J
