Backend/rtl/DATA_SYNC.v
module DATA_SYNC #(
    parameter NUM_STAGES = 2,
    parameter BUS_WIDTH = 8
) (
    input wire [BUS_WIDTH-1:0] unsync_bus,
    input wire                 bus_enable,
    input wire                 CLK,
    input wire                 RST,
    output reg [BUS_WIDTH-1:0] sync_bus,
    output reg                 enable_pulse
);
    reg [NUM_STAGES-1:0] sync_ff;
    reg pulse_ff;
    wire pulse_gen_out;
    wire [BUS_WIDTH-1:0] mux_out;
    integer i;

    assign pulse_gen_out = (!pulse_ff) && sync_ff[NUM_STAGES-1];
    assign mux_out = pulse_gen_out ? unsync_bus : sync_bus;

    // Enable signal synchronization
    always @(posedge CLK or negedge RST) begin
        if (!RST) begin
            sync_ff <= 'b0;
            pulse_ff <= 1'b0;
        end else begin
            sync_ff[0] <= bus_enable;
            for (i=1 ; i<NUM_STAGES ; i=i+1) begin
                sync_ff[i] <= sync_ff[i-1];
            end
            pulse_ff <= sync_ff[NUM_STAGES-1];
        end
    end

    // Data synchronization
    always @(posedge CLK or negedge RST) begin
        if (!RST) begin
            enable_pulse <= 1'b0;
            sync_bus <= 'b0;
        end else begin
            enable_pulse <= pulse_gen_out;
            sync_bus <= mux_out;
        end
    end

endmodule

RTL/Data_Synchronizer/DATA_SYNC_tb.v
`timescale 1ns / 1ps
module DATA_SYNC_tb();
    parameter CLOCK_PERIOD = 10;
    parameter NUM_STAGES = 2;
    parameter BUS_WIDTH = 8;
    // Testbench signals
    reg [BUS_WIDTH-1:0]  unsync_bus_tb;
    reg                  bus_enable_tb;
    reg                  CLK_tb;
    reg                  RST_tb;
    wire [BUS_WIDTH-1:0] sync_bus_tb;
    wire                 enable_pulse_tb;


    // CLK Generator
    always #(CLOCK_PERIOD/2) CLK_tb = ~CLK_tb;

    // Design Instantiation
    DATA_SYNC #(
        .NUM_STAGES(NUM_STAGES),
        .BUS_WIDTH(BUS_WIDTH)
    ) DUT (
        .unsync_bus(unsync_bus_tb),
        .bus_enable(bus_enable_tb),
        .CLK(CLK_tb),
        .RST(RST_tb),
        .sync_bus(sync_bus_tb),
        .enable_pulse(enable_pulse_tb)
    );

    initial begin
        $dumpfile("DATA_SYNC.vcd");           // Save waveform to this file     
        $dumpvars;                            // Dump all variables recursively 

        initialize;
        reset;

        $display("=== Normal Data Transfer Tests ===");
        drive_and_check('hA3);
        drive_and_check('hF3);
        drive_and_check('h55);

        $display("\n=== Corner Case: bus_enable stuck at 0 ===");
        unsync_bus_tb = 'h77;
        bus_enable_tb = 1'b0;
        #((NUM_STAGES + 1) * CLOCK_PERIOD);
        if (sync_bus_tb == 'h55) begin
            $display("PASS: Data unchanged when bus_enable=0: sync_bus=%0h",sync_bus_tb);
        end else begin
            $display("FAIL: Data changed unexpectedly: expected 55, got %0h",sync_bus_tb);
        end

        $display("\n=== Corner Case: bus_enable stuck at 1 ===");
        unsync_bus_tb = 'h99;
        bus_enable_tb = 1'b1;
        #((NUM_STAGES + 1) * CLOCK_PERIOD);
        unsync_bus_tb = 'hAA;
        #((NUM_STAGES + 1) * CLOCK_PERIOD);
        unsync_bus_tb = 'hBB;
        #((NUM_STAGES + 1) * CLOCK_PERIOD);
        if (sync_bus_tb == 'h99) begin
            $display("PASS: Only first data captured when bus_enable stuck at 1: %0h",sync_bus_tb);
        end else begin
            $display("FAIL: Expected 99, got %0h",sync_bus_tb);
        end

        $display("\n=== Back to Normal Data Transfer Tests ===");
        bus_enable_tb = 1'b0; 
        #(2*CLOCK_PERIOD);
        drive_and_check('h44);
        
        $stop;
    end


    // Tasks Definitions 
    task initialize;
    begin
        CLK_tb = 1'b0;
        unsync_bus_tb = 'b0;
        bus_enable_tb = 1'b0;
    end
    endtask

    task reset;
    begin
        RST_tb = 1'b1;
        #(CLOCK_PERIOD)
        RST_tb = 1'b0;
        #(CLOCK_PERIOD)
        RST_tb = 1'b1;
    end
    endtask

    task drive_and_check (input [BUS_WIDTH-1:0] data);
    begin        
        unsync_bus_tb = data;
        bus_enable_tb = 1'b1;
        #(CLOCK_PERIOD);
        bus_enable_tb = 1'b0;
        
        #((NUM_STAGES + 1) * CLOCK_PERIOD);
        
        // Check the results
        if (sync_bus_tb != unsync_bus_tb) begin
            $display("Data mismatch: unsync_bus = %0h and sync_bus = %0h",unsync_bus_tb,sync_bus_tb);
        end else begin
            $display("Test passed: Data correctly synchronized = %h",sync_bus_tb);
        end
        
    end
    endtask
endmodule

RTL/Data_Synchronizer/DATA_SYNC.vcd
$date
	Wed Sep  3 17:40:32 2025
$end
$version
	QuestaSim Version 2021.1
$end
$timescale
	1ps
$end

$scope module DATA_SYNC_tb $end
$var parameter 32 ! CLOCK_PERIOD $end
$var parameter 32 " NUM_STAGES $end
$var parameter 32 # BUS_WIDTH $end
$var reg 8 $ unsync_bus_tb [7:0] $end
$var reg 1 % bus_enable_tb $end
$var reg 1 & CLK_tb $end
$var reg 1 ' RST_tb $end
$var wire 1 ( sync_bus_tb [7] $end
$var wire 1 ) sync_bus_tb [6] $end
$var wire 1 * sync_bus_tb [5] $end
$var wire 1 + sync_bus_tb [4] $end
$var wire 1 , sync_bus_tb [3] $end
$var wire 1 - sync_bus_tb [2] $end
$var wire 1 . sync_bus_tb [1] $end
$var wire 1 / sync_bus_tb [0] $end
$var wire 1 0 enable_pulse_tb $end

$scope task initialize $end
$upscope $end

$scope task reset $end
$upscope $end

$scope task drive_and_check $end
$var reg 8 1 data [7:0] $end
$upscope $end

$scope module DUT $end
$var parameter 32 2 NUM_STAGES $end
$var parameter 32 3 BUS_WIDTH $end
$var wire 1 4 unsync_bus [7] $end
$var wire 1 5 unsync_bus [6] $end
$var wire 1 6 unsync_bus [5] $end
$var wire 1 7 unsync_bus [4] $end
$var wire 1 8 unsync_bus [3] $end
$var wire 1 9 unsync_bus [2] $end
$var wire 1 : unsync_bus [1] $end
$var wire 1 ; unsync_bus [0] $end
$var wire 1 < bus_enable $end
$var wire 1 = CLK $end
$var wire 1 > RST $end
$var reg 8 ? sync_bus [7:0] $end
$var reg 1 @ enable_pulse $end
$var reg 2 A sync_ff [1:0] $end
$var reg 1 B pulse_ff $end
$var wire 1 C pulse_gen_out $end
$var wire 1 D mux_out [7] $end
$var wire 1 E mux_out [6] $end
$var wire 1 F mux_out [5] $end
$var wire 1 G mux_out [4] $end
$var wire 1 H mux_out [3] $end
$var wire 1 I mux_out [2] $end
$var wire 1 J mux_out [1] $end
$var wire 1 K mux_out [0] $end
$var integer 32 L i $end
$upscope $end
$upscope $end
$enddefinitions $end
#0
$dumpvars
b0 $
0%
0&
1'
bx ?
x@
bx A
xB
bx 1
b1010 !
b10 "
b1000 #
b10 2
b1000 3
bx L
x/
x.
x-
x,
x+
x*
x)
x(
x0
xC
xK
xJ
xI
xH
xG
xF
xE
xD
1>
0=
0<
0;
0:
09
08
07
06
05
04
$end
#5000
1&
1=
b1 L
b10 L
bx0 A
#10000
0'
0&
0>
0=
b0 A
0B
0@
b0 ?
0C
00
0/
0.
0-
0,
0+
0*
0)
0(
0K
0J
0I
0H
0G
0F
0E
0D
#15000
1&
1=
#20000
1'
b10100011 1
b10100011 $
1%
0&
1;
1:
16
14
1<
1>
0=
#25000
1&
1=
b1 L
b10 L
b1 A
#30000
0%
0&
0<
0=
#35000
1&
1=
b1 L
b10 L
b0 A
b10 A
1C
1K
1J
1F
1D
#40000
0&
0=
#45000
1&
1=
b1 L
b10 L
1@
b10100011 ?
b0 A
1B
0C
10
1/
1.
1*
1(
#50000
0&
0=
#55000
1&
1=
b1 L
b10 L
0B
0@
00
#60000
b11110011 1
b11110011 $
1%
0&
17
15
1<
0=
#65000
1&
1=
b1 L
b10 L
b1 A
#70000
0%
0&
0<
0=
#75000
1&
1=
b1 L
b10 L
b0 A
b10 A
1C
1G
1E
#80000
0&
0=
#85000
1&
1=
b1 L
b10 L
1@
b11110011 ?
b0 A
1B
0C
10
1+
1)
#90000
0&
0=
#95000
1&
1=
b1 L
b10 L
0B
0@
00
#100000
b1010101 1
b1010101 $
1%
0&
0:
19
06
04
1<
0=
#105000
1&
1=
b1 L
b10 L
b1 A
#110000
0%
0&
0<
0=
#115000
1&
1=
b1 L
b10 L
b0 A
b10 A
1C
0J
1I
0F
0D
#120000
0&
0=
#125000
1&
1=
b1 L
b10 L
1@
b1010101 ?
b0 A
1B
0C
10
0.
1-
0*
0(
#130000
0&
0=
#135000
1&
1=
b1 L
b10 L
0B
0@
00
#140000
b1110111 $
0&
1:
16
0=
#145000
1&
1=
b1 L
b10 L
#150000
0&
0=
#155000
1&
1=
#160000
0&
0=
#165000
1&
1=
#170000
b10011001 $
1%
0&
0:
09
18
06
05
14
1<
0=
#175000
1&
1=
b1 L
b10 L
b1 A
#180000
0&
0=
#185000
1&
1=
b1 L
b10 L
b11 A
1C
0I
1H
0E
1D
#190000
0&
0=
#195000
1&
1=
b1 L
b10 L
1@
b10011001 ?
1B
0C
10
0-
1,
0)
1(
#200000
b10101010 $
0&
0;
1:
07
16
0=
#205000
1&
1=
b1 L
b10 L
0@
00
#210000
0&
0=
#215000
1&
1=
#220000
0&
0=
#225000
1&
1=
#230000
b10111011 $
0&
1;
17
0=
#235000
1&
1=
#240000
0&
0=
#245000
1&
1=
#250000
0&
0=
#255000
1&
1=
#260000
0%
0&
0<
0=
#265000
1&
1=
b1 L
b10 L
b10 A
#270000
0&
0=
#275000
1&
1=
b1 L
b10 L
b0 A
#280000
b1000100 1
b1000100 $
1%
0&
0;
0:
19
08
07
06
15
04
1<
0=
#285000
1&
1=
b1 L
b10 L
b1 A
0B
#290000
0%
0&
0<
0=
#295000
1&
1=
b1 L
b10 L
b0 A
b10 A
1C
0K
1I
0H
0G
1E
0D
#300000
0&
0=
#305000
1&
1=
b1 L
b10 L
1@
b1000100 ?
b0 A
1B
0C
10
0/
1-
0,
0+
1)
0(
#310000
0&
0=
#315000
1&
1=
b1 L
b10 L
0B
0@
00
