RTL/UART_RX/FSM.sv
module FSM (
    input wire       CLK,
    input wire       RST,
    input wire       PAR_EN,
    input wire       RX_IN,
    input wire       par_err,
    input wire       strt_glitch,
    input wire       stp_err,
    input wire [3:0] bit_cnt,
    input wire [5:0] edge_cnt,
    input wire [5:0] Prescale,
    output reg       enable,
    output reg       dat_samp_en,
    output reg       deser_en,
    output reg       data_valid,
    output reg       stp_chk_en,
    output reg       strt_chk_en,
    output reg       par_chk_en
);

    typedef enum bit [2:0] {
        IDLE = 3'b000,
        START = 3'b001,
        DATA = 3'b010,
        PARITY = 3'b011,
        STOP = 3'b100
    } state_e;
    
    state_e current_state, next_state;

    // State Transition 	
    always @(posedge CLK or negedge RST) begin
        if (!RST) begin
            current_state <= IDLE;
        end else begin
            current_state <= next_state;
        end
    end

    // Next State Logic
    always @(*) begin
        case (current_state)
            IDLE: begin
                if (!RX_IN) begin
                    next_state = START;
                end else begin
                    next_state = IDLE;
                end
            end
            START: begin
                if (!strt_glitch && (bit_cnt == 4'd1)) begin
                    next_state = DATA;
                end else if (strt_glitch) begin
                    next_state = IDLE;
                end else begin
                    next_state = START;
                end
            end
            DATA: begin
                if (PAR_EN && bit_cnt == 4'd9) begin
                    next_state = PARITY;
                end else if (!PAR_EN && bit_cnt == 4'd9) begin
                    next_state = STOP;
                end else begin
                    next_state = DATA;
                end
            end
            PARITY: begin
                if (!par_err && bit_cnt == 4'd10) begin
                    next_state = STOP;
                end else begin
                    next_state = PARITY;
                end
            end
            STOP: begin
                if (!stp_err && RX_IN && bit_cnt == 4'd0) begin
                    next_state = IDLE;
                end else if (!stp_err && !RX_IN && bit_cnt == 4'd0) begin
                    next_state = START;
                end else begin
                    next_state = STOP;
                end
            end
            default: begin
                next_state = IDLE;
            end
        endcase
    end


    // Output Logic
    always @(*) begin
        // Default values
        enable      = 1'b0;
        dat_samp_en = 1'b0;
        deser_en    = 1'b0;
        data_valid  = 1'b0;
        stp_chk_en  = 1'b0;
        strt_chk_en = 1'b0;
        par_chk_en  = 1'b0;
        case (current_state)
            IDLE: begin
                dat_samp_en = 1'b1;
                if (!RX_IN) begin
                    enable = 1'b1;
                end else begin
                    enable = 1'b0;
                end
            end
            START: begin
                dat_samp_en = 1'b1;
                enable = 1'b1;
                if (edge_cnt == ((Prescale >> 1'b1) + 2'd3)) begin
                    strt_chk_en = 1'b1;
                end else begin
                    strt_chk_en = 1'b0;
                end
            end
            DATA: begin
                dat_samp_en = 1'b1;
                enable = 1'b1;
                if (edge_cnt == ((Prescale >> 1'b1) + 2'd3)) begin
                    deser_en = 1'b1;
                end else begin
                    deser_en = 1'b0;
                end
            end
            PARITY: begin
                dat_samp_en = 1'b1;
                enable = 1'b1;
                if (edge_cnt == ((Prescale >> 1'b1) + 2'd3)) begin
                    par_chk_en = 1'b1;
                end else begin
                    par_chk_en = 1'b0;
                end
            end
            STOP: begin
                dat_samp_en = 1'b1;
                enable = 1'b1;
                if (!par_err && !stp_err && (edge_cnt == ((Prescale >> 1'b1) + 2'd3))) begin
                    data_valid = 1'b1;
                end else begin
                    data_valid = 1'b0;
                end

                if (edge_cnt == ((Prescale >> 1'b1) + 2'd3)) begin
                    stp_chk_en = 1'b1;
                end else begin
                    stp_chk_en = 1'b0;
                end
            end
            default: begin
                enable      = 1'b0;
                dat_samp_en = 1'b0;
                deser_en    = 1'b0;
                data_valid  = 1'b0;
                stp_chk_en  = 1'b0;
                strt_chk_en = 1'b0;
                par_chk_en  = 1'b0;
            end
        endcase
    end
endmodule

Backend/rtl/strt_check.v
module strt_check (
    input wire       CLK,
    input wire       RST,
    input wire       strt_chk_en,
    input wire       sampled_bit,
    output reg       strt_glitch
);

    always @(posedge CLK or negedge RST) begin
        if (!RST) begin
            strt_glitch <= 1'b0;
        end else if (strt_chk_en) begin
            strt_glitch <= sampled_bit;
        end else begin
            strt_glitch <= 1'b0;
        end
    end
endmodule

Backend/rtl/stop_check.v
module stop_check (
    input wire       CLK,
    input wire       RST,
    input wire       stp_chk_en,
    input wire       sampled_bit,
    output reg       stp_err
);

    always @(posedge CLK or negedge RST) begin
        if (!RST) begin
            stp_err <= 1'b0;
        end else if (stp_chk_en) begin
            stp_err <= ~(sampled_bit);
        end 
    end
endmodule

Backend/rtl/parity_check.v
module parity_check #(parameter DATA_WIDTH = 8)(
    input wire                  CLK,
    input wire                  RST,
    input wire                  PAR_TYP,
    input wire                  par_chk_en,
    input wire                  sampled_bit,
    input wire [DATA_WIDTH-1:0] P_DATA,
    output reg                  par_err
);
    wire parity_bit;

    assign parity_bit = (PAR_TYP) ? ~(^P_DATA) : (^P_DATA);

    always @(posedge CLK or negedge RST) begin
        if (!RST) begin
            par_err <= 1'b0;
        end else if (par_chk_en) begin
            par_err <= (parity_bit != sampled_bit);
        end
    end
endmodule

RTL/UART_RX/edge_bit_counter.v
module edge_bit_counter (
    input wire       CLK,
    input wire       RST,
    input wire       enable,
    input wire       PAR_EN,
    input wire [5:0] Prescale,
    output reg [5:0] edge_cnt,
    output reg [3:0] bit_cnt
);
    always @(posedge CLK or negedge RST) begin
        if (!RST) begin
            edge_cnt <= 6'b0;
            bit_cnt <= 4'b0;
        end else if (enable && (edge_cnt < (Prescale - 6'b1))) begin
            edge_cnt <= edge_cnt + 1'b1;
        end else if (enable && (edge_cnt == (Prescale - 6'b1))) begin
            edge_cnt <= 6'b0;
            if (PAR_EN && (bit_cnt == 4'd10)) begin
                bit_cnt <= 4'b0;
            end else if (!PAR_EN && (bit_cnt == 4'd9)) begin 
                bit_cnt <= 4'b0;
            end else begin
                bit_cnt <= bit_cnt + 1'b1;
            end
        end else begin
            bit_cnt <= 4'b0;
        end
    end
endmodule

Backend/rtl/deserializer.v
module deserializer #(parameter DATA_WIDTH = 8)(
    input wire                  CLK,
    input wire                  RST,
    input wire                  sampled_bit,
    input wire                  deser_en,
    input wire [5:0]            edge_count, 
    input wire [5:0]            Prescale, 
    output reg [DATA_WIDTH-1:0] P_DATA
);

    reg [2:0] counter;

    always @(posedge CLK or negedge RST) begin
        if (!RST) begin
            P_DATA <= 'b0;
            counter <= 8'b0;
        end else if (deser_en) begin
            P_DATA[counter] <= sampled_bit;
            counter <= counter + 1'b1;
        end
    end  
endmodule

Backend/rtl/data_sampling.v
module data_sampling (
    input wire       CLK,
    input wire       RST,
    input wire       RX_IN,
    input wire       dat_samp_en,
    input wire [5:0] edge_cnt,
    input wire [5:0] Prescale,
    output reg       sampled_bit
);

    reg sample1, sample2, sample3;

    always @(posedge CLK or negedge RST) begin
        if (!RST) begin
            sample1 <= 1'b0;
            sample2 <= 1'b0;
            sample3 <= 1'b0;
        end else if (dat_samp_en) begin
            case (edge_cnt)
                (Prescale / 2'd2) - 1'd1:   sample1 <= RX_IN;
                (Prescale / 2'd2):          sample2 <= RX_IN;
                (Prescale / 2'd2) + 1'd1:   sample3 <= RX_IN;
                (Prescale >> 1'b1) + 2'd2:  sampled_bit <= (sample1 & sample2) | (sample1 & sample3) | (sample2 & sample3);
                default: begin
                    sample1 <= 1'b0;
                    sample2 <= 1'b0;
                    sample3 <= 1'b0;
                end
            endcase
        end 
    end
endmodule

RTL/UART_RX/UART_RX.v
module UART_RX #(parameter DATA_WIDTH = 8)(
    input wire                   CLK,
    input wire                   RST,
    input wire                   RX_IN,
    input wire                   PAR_TYP,
    input wire                   PAR_EN,
    input wire  [5:0]            Prescale,
    output wire                  data_valid,
    output wire                  Parity_Error,
    output wire                  Stop_Error,
    output wire [DATA_WIDTH-1:0] P_DATA
);
    wire enable, par_chk_en, strt_chk_en, strt_glitch, stp_chk_en, deser_en, dat_samp_en, sampled_bit;
    wire [5:0] edge_cnt;
    wire [3:0] bit_cnt;

    data_sampling data_samp (
        .CLK(CLK),
        .RST(RST),
        .RX_IN(RX_IN),
        .dat_samp_en(dat_samp_en),
        .edge_cnt(edge_cnt),
        .sampled_bit(sampled_bit),
        .Prescale(Prescale)
    );

    deserializer #(.DATA_WIDTH(DATA_WIDTH)) deserial (
        .CLK(CLK),
        .RST(RST),
        .deser_en(deser_en),
        .sampled_bit(sampled_bit),
        .edge_count(edge_cnt),
        .Prescale(Prescale),
        .P_DATA(P_DATA)
    );

    edge_bit_counter counter (
        .CLK(CLK),
        .RST(RST),
        .enable(enable),
        .PAR_EN(PAR_EN),
        .Prescale(Prescale),
        .edge_cnt(edge_cnt),
        .bit_cnt(bit_cnt)
    );

    parity_check #(.DATA_WIDTH(DATA_WIDTH)) par_chk (
        .CLK(CLK),
        .RST(RST),
        .PAR_TYP(PAR_TYP),
        .par_chk_en(par_chk_en),
        .sampled_bit(sampled_bit),
        .P_DATA(P_DATA),
        .par_err(Parity_Error)
    );

    stop_check stp_chk (
        .CLK(CLK),
        .RST(RST),
        .sampled_bit(sampled_bit),
        .stp_chk_en(stp_chk_en),
        .stp_err(Stop_Error)
    );

    strt_check strt_chk (
        .CLK(CLK),
        .RST(RST),
        .sampled_bit(sampled_bit),
        .strt_chk_en(strt_chk_en),
        .strt_glitch(strt_glitch)
    );

    FSM fsm (
        .CLK(CLK),
        .RST(RST),
        .PAR_EN(PAR_EN),
        .RX_IN(RX_IN),
        .par_err(Parity_Error),
        .strt_glitch(strt_glitch),
        .stp_err(Stop_Error),
        .edge_cnt(edge_cnt),
        .bit_cnt(bit_cnt),
        .Prescale(Prescale),
        .enable(enable),
        .dat_samp_en(dat_samp_en),
        .deser_en(deser_en),
        .data_valid(data_valid),
        .strt_chk_en(strt_chk_en),
        .stp_chk_en(stp_chk_en),
        .par_chk_en(par_chk_en)
    );
endmodule

RTL/UART_RX/UART_RX_tb.v
`timescale 1ns / 1ps
module UART_RX_tb ();
    // Testbench signals
    reg        CLK_tx_tb;
    reg        CLK_rx;
    reg        RST_tb;
    reg        RX_IN_tb;
    reg        PAR_TYP_tb;
    reg        PAR_EN_tb;
    reg [5:0]  Prescale_tb;
    wire       data_valid_tb;
    wire       Parity_Error_tb;
    wire       Stop_Error_tb;
    wire [7:0] P_DATA_tb;

    parameter CLOCK_TX_PERIOD = 8680;
    integer i;

    // Clock_tx Generator
    always #(CLOCK_TX_PERIOD/2) CLK_tx_tb = ~CLK_tx_tb;

    // Clock_rx Generator
    always #(CLOCK_TX_PERIOD/(2 * Prescale_tb)) CLK_rx = ~CLK_rx;

    // Design Instantiation
    UART_RX DUT (
        .CLK(CLK_rx),
        .RST(RST_tb),
        .RX_IN(RX_IN_tb),
        .PAR_TYP(PAR_TYP_tb),
        .PAR_EN(PAR_EN_tb),
        .Prescale(Prescale_tb),
        .data_valid(data_valid_tb),
        .Parity_Error(Parity_Error_tb),
        .Stop_Error(Stop_Error_tb),
        .P_DATA(P_DATA_tb)
    );

    initial begin
        $dumpfile("UART_RX.vcd");           // Save waveform to this file     
        $dumpvars;                          // Dump all variables recursively 

        initialize;
        reset;

        // ---- Test 1: No parity, prescale=8 ----
        $display("\n--- Test 1: No parity, Data = 0b10100101, Prescale = 8 ---");
        receive_withoutparity(10'b1101001010,6'd8,8'b10100101); 

        // ---- Test 2: Even parity, prescale=8 ----
        $display("\n--- Test 2: Even parity, Data = 0b10100101, Prescale = 8 ---");
        receive_withparity({1'b1,^(8'b10100101),8'b10100101,1'b0},1'b0,6'd8,8'b10100101);

        // ---- Test 3: Odd parity, prescale=8 ----
        $display("\n--- Test 3: Odd parity, Data = 0b10100101, Prescale = 8 ---");
        receive_withparity({1'b1,~(^(8'b10100101)),8'b10100101,1'b0},1'b1,6'd8,8'b10100101);

        // ---- Test 4: No parity, prescale=16 ----
        $display("\n--- Test 4: No parity, Data = 0b10110101, Prescale = 16 ---");
        receive_withoutparity(10'b1101101010,6'd16,8'b10110101); 

        // ---- Test 5: Even parity, prescale=16 ----
        $display("\n--- Test 5: Even parity, Data = 0b10110101, Prescale = 16 ---");
        receive_withparity({1'b1,^(8'b10110101),8'b10110101,1'b0},1'b0,6'd16,8'b10110101);

        // ---- Test 6: Odd parity, prescale=16 ----
        $display("\n--- Test 6: Odd parity, Data = 0b10110101, Prescale = 16 ---");
        receive_withparity({1'b1,~(^(8'b10110101)),8'b10110101,1'b0},1'b1,6'd16,8'b10110101);

        // ---- Test 7: No parity, prescale=32 ----
        $display("\n--- Test 7: No parity, Data = 0b10110001, Prescale = 32 ---");
        receive_withoutparity(10'b1101100010,6'd32,8'b10110001); 

        // ---- Test 8: Even parity, prescale=32 ----
        $display("\n--- Test 8: Even parity, Data = 0b10110001, Prescale = 32 ---");
        receive_withparity({1'b1,^(8'b10110001),8'b10110001,1'b0},1'b0,6'd32,8'b10110001);

        // ---- Test 9: Odd parity, prescale=32 ----
        $display("\n--- Test 9: Odd parity, Data = 0b10110001, Prescale = 32 ---");
        receive_withparity({1'b1,~(^(8'b10110001)),8'b10110001,1'b0},1'b1,6'd32,8'b10110001);

        // ---- Test 10: Return to idle then receive new frame ----
        $display("\n--- Test 10: Return to idle then receive new frame ---");
        RX_IN_tb = 1'b1;
        #(CLOCK_TX_PERIOD);
        receive_withoutparity(10'b1101100110,6'd8,8'b10110011); 

        // ---- Test 11: Start glitch ----
        $display("\n--- Test 11: Start glitch ---");
        RX_IN_tb = 1'b1;
        #(CLOCK_TX_PERIOD);
        RX_IN_tb = 1'b0;
        repeat(2) #(CLOCK_TX_PERIOD/(Prescale_tb));
        RX_IN_tb = 1'b1;
        @(posedge DUT.strt_chk.strt_glitch);
        $display("PASS: Start glitch detected at %0t",$time);
        #(CLOCK_TX_PERIOD);
        if (!DUT.strt_chk.strt_glitch)
            $display("PASS: Start glitch cleared");
        else
            $display("FAIL: Start glitch is sticky");


        // ---- Test 12: No parity, prescale=8 ----
        $display("\n--- Test 12: No parity, Data = 0b10111001, Prescale = 8 ---");
        receive_withoutparity(10'b1101110010,6'd8,8'b10111001); 

        // ---- Test 13: Even parity, prescale=8 ----
        $display("\n--- Test 13: Even parity, Data = 0b10111001, Prescale = 8 ---");
        receive_withparity({1'b1,^(8'b10111001),8'b10111001,1'b0},1'b0,6'd8,8'b10111001);

        // ---- Test 14: Odd parity, prescale=8 ----
        $display("\n--- Test 14: Odd parity, Data = 0b10111001, Prescale = 8 ---");
        receive_withparity({1'b1,~(^(8'b10111001)),8'b10111001,1'b0},1'b1,6'd8,8'b10111001);

        $stop;
    end


    // Tasks Definitions 
    task initialize;
    begin
        RX_IN_tb = 1'b1;
        Prescale_tb = 6'd8;
        PAR_EN_tb = 1'b0;
        PAR_TYP_tb = 1'b0;
        CLK_tx_tb = 1'b0;
        CLK_rx = 1'b0;
    end
    endtask

    task reset;
    begin
        RST_tb = 1'b1;
        #(CLOCK_TX_PERIOD)
        RST_tb = 1'b0;
        #(CLOCK_TX_PERIOD)
        RST_tb = 1'b1;
    end
    endtask

    task receive_withparity(input [10:0] data, input parity_type, input [5:0] prescale, input [7:0] exp_data);
    begin
        Prescale_tb = prescale;
        PAR_EN_tb = 1'b1;
        PAR_TYP_tb = parity_type;

        for (i=0 ; i<11 ; i=i+1) begin
            RX_IN_tb = data[i];
            #(CLOCK_TX_PERIOD);
        end
        if ((exp_data == P_DATA_tb) && !Parity_Error_tb && !Stop_Error_tb)
            $display("PASS: Received 0b%0b correctly with parity",P_DATA_tb);
        else if (Parity_Error_tb)
            $display("FAIL: Parity error detected");
        else if (Stop_Error_tb)
            $display("FAIL: Stop bit error detected");
        else
            $display("FAIL: Data mismatch (got 0b%0b)",P_DATA_tb);
    end
    endtask

    task receive_withoutparity(input [9:0] data, input [5:0] prescale, input [7:0] exp_data);
    begin
        Prescale_tb = prescale;
        PAR_EN_tb = 1'b0;

        for (i=0 ; i<10 ; i=i+1) begin
            RX_IN_tb = data[i];
            #(CLOCK_TX_PERIOD);
        end
        if ((exp_data == P_DATA_tb) && !Parity_Error_tb && !Stop_Error_tb)
            $display("PASS: Received 0b%0b correctly",P_DATA_tb);
        else if (Stop_Error_tb)
            $display("FAIL: Stop bit error detected");
        else
            $display("FAIL: Data mismatch (got 0b%0b)",P_DATA_tb);
    end
    endtask
endmodule

RTL/UART_RX/UART_RX.vcd
$date
	Sun Sep 21 17:33:34 2025
$end
$version
	QuestaSim Version 2021.1
$end
$timescale
	1ps
$end

$scope module UART_RX_tb $end
$var parameter 32 ! CLOCK_TX_PERIOD $end
$var reg 1 " CLK_tx_tb $end
$var reg 1 # CLK_rx $end
$var reg 1 $ RST_tb $end
$var reg 1 % RX_IN_tb $end
$var reg 1 & PAR_TYP_tb $end
$var reg 1 ' PAR_EN_tb $end
$var reg 6 ( Prescale_tb [5:0] $end
$var wire 1 ) data_valid_tb $end
$var wire 1 * Parity_Error_tb $end
$var wire 1 + Stop_Error_tb $end
$var wire 1 , P_DATA_tb [7] $end
$var wire 1 - P_DATA_tb [6] $end
$var wire 1 . P_DATA_tb [5] $end
$var wire 1 / P_DATA_tb [4] $end
$var wire 1 0 P_DATA_tb [3] $end
$var wire 1 1 P_DATA_tb [2] $end
$var wire 1 2 P_DATA_tb [1] $end
$var wire 1 3 P_DATA_tb [0] $end
$var integer 32 4 i $end

$scope task initialize $end
$upscope $end

$scope task reset $end
$upscope $end

$scope task receive_withparity $end
$var reg 11 5 data [10:0] $end
$var reg 1 6 parity_type $end
$var reg 6 7 prescale [5:0] $end
$var reg 8 8 exp_data [7:0] $end
$upscope $end

$scope task receive_withoutparity $end
$var reg 10 9 data [9:0] $end
$var reg 6 : prescale [5:0] $end
$var reg 8 ; exp_data [7:0] $end
$upscope $end

$scope module DUT $end
$var parameter 32 < DATA_WIDTH $end
$var wire 1 = CLK $end
$var wire 1 > RST $end
$var wire 1 ? RX_IN $end
$var wire 1 @ PAR_TYP $end
$var wire 1 A PAR_EN $end
$var wire 1 B Prescale [5] $end
$var wire 1 C Prescale [4] $end
$var wire 1 D Prescale [3] $end
$var wire 1 E Prescale [2] $end
$var wire 1 F Prescale [1] $end
$var wire 1 G Prescale [0] $end
$var wire 1 ) data_valid $end
$var wire 1 * Parity_Error $end
$var wire 1 + Stop_Error $end
$var wire 1 , P_DATA [7] $end
$var wire 1 - P_DATA [6] $end
$var wire 1 . P_DATA [5] $end
$var wire 1 / P_DATA [4] $end
$var wire 1 0 P_DATA [3] $end
$var wire 1 1 P_DATA [2] $end
$var wire 1 2 P_DATA [1] $end
$var wire 1 3 P_DATA [0] $end
$var wire 1 H enable $end
$var wire 1 I par_chk_en $end
$var wire 1 J strt_chk_en $end
$var wire 1 K strt_glitch $end
$var wire 1 L stp_chk_en $end
$var wire 1 M deser_en $end
$var wire 1 N dat_samp_en $end
$var wire 1 O sampled_bit $end
$var wire 1 P edge_cnt [5] $end
$var wire 1 Q edge_cnt [4] $end
$var wire 1 R edge_cnt [3] $end
$var wire 1 S edge_cnt [2] $end
$var wire 1 T edge_cnt [1] $end
$var wire 1 U edge_cnt [0] $end
$var wire 1 V bit_cnt [3] $end
$var wire 1 W bit_cnt [2] $end
$var wire 1 X bit_cnt [1] $end
$var wire 1 Y bit_cnt [0] $end

$scope module data_samp $end
$var wire 1 = CLK $end
$var wire 1 > RST $end
$var wire 1 ? RX_IN $end
$var wire 1 N dat_samp_en $end
$var wire 1 P edge_cnt [5] $end
$var wire 1 Q edge_cnt [4] $end
$var wire 1 R edge_cnt [3] $end
$var wire 1 S edge_cnt [2] $end
$var wire 1 T edge_cnt [1] $end
$var wire 1 U edge_cnt [0] $end
$var wire 1 B Prescale [5] $end
$var wire 1 C Prescale [4] $end
$var wire 1 D Prescale [3] $end
$var wire 1 E Prescale [2] $end
$var wire 1 F Prescale [1] $end
$var wire 1 G Prescale [0] $end
$var reg 1 Z sampled_bit $end
$var reg 1 [ sample1 $end
$var reg 1 \ sample2 $end
$var reg 1 ] sample3 $end
$upscope $end

$scope module deserial $end
$var parameter 32 ^ DATA_WIDTH $end
$var wire 1 = CLK $end
$var wire 1 > RST $end
$var wire 1 O sampled_bit $end
$var wire 1 M deser_en $end
$var wire 1 P edge_count [5] $end
$var wire 1 Q edge_count [4] $end
$var wire 1 R edge_count [3] $end
$var wire 1 S edge_count [2] $end
$var wire 1 T edge_count [1] $end
$var wire 1 U edge_count [0] $end
$var wire 1 B Prescale [5] $end
$var wire 1 C Prescale [4] $end
$var wire 1 D Prescale [3] $end
$var wire 1 E Prescale [2] $end
$var wire 1 F Prescale [1] $end
$var wire 1 G Prescale [0] $end
$var reg 8 _ P_DATA [7:0] $end
$var reg 3 ` counter [2:0] $end
$upscope $end

$scope module counter $end
$var wire 1 = CLK $end
$var wire 1 > RST $end
$var wire 1 H enable $end
$var wire 1 A PAR_EN $end
$var wire 1 B Prescale [5] $end
$var wire 1 C Prescale [4] $end
$var wire 1 D Prescale [3] $end
$var wire 1 E Prescale [2] $end
$var wire 1 F Prescale [1] $end
$var wire 1 G Prescale [0] $end
$var reg 6 a edge_cnt [5:0] $end
$var reg 4 b bit_cnt [3:0] $end
$upscope $end

$scope module par_chk $end
$var parameter 32 c DATA_WIDTH $end
$var wire 1 = CLK $end
$var wire 1 > RST $end
$var wire 1 @ PAR_TYP $end
$var wire 1 I par_chk_en $end
$var wire 1 O sampled_bit $end
$var wire 1 , P_DATA [7] $end
$var wire 1 - P_DATA [6] $end
$var wire 1 . P_DATA [5] $end
$var wire 1 / P_DATA [4] $end
$var wire 1 0 P_DATA [3] $end
$var wire 1 1 P_DATA [2] $end
$var wire 1 2 P_DATA [1] $end
$var wire 1 3 P_DATA [0] $end
$var reg 1 d par_err $end
$var wire 1 e parity_bit $end
$upscope $end

$scope module stp_chk $end
$var wire 1 = CLK $end
$var wire 1 > RST $end
$var wire 1 L stp_chk_en $end
$var wire 1 O sampled_bit $end
$var reg 1 f stp_err $end
$upscope $end

$scope module strt_chk $end
$var wire 1 = CLK $end
$var wire 1 > RST $end
$var wire 1 J strt_chk_en $end
$var wire 1 O sampled_bit $end
$var reg 1 g strt_glitch $end
$upscope $end

$scope module fsm $end
$var wire 1 = CLK $end
$var wire 1 > RST $end
$var wire 1 A PAR_EN $end
$var wire 1 ? RX_IN $end
$var wire 1 * par_err $end
$var wire 1 K strt_glitch $end
$var wire 1 + stp_err $end
$var wire 1 V bit_cnt [3] $end
$var wire 1 W bit_cnt [2] $end
$var wire 1 X bit_cnt [1] $end
$var wire 1 Y bit_cnt [0] $end
$var wire 1 P edge_cnt [5] $end
$var wire 1 Q edge_cnt [4] $end
$var wire 1 R edge_cnt [3] $end
$var wire 1 S edge_cnt [2] $end
$var wire 1 T edge_cnt [1] $end
$var wire 1 U edge_cnt [0] $end
$var wire 1 B Prescale [5] $end
$var wire 1 C Prescale [4] $end
$var wire 1 D Prescale [3] $end
$var wire 1 E Prescale [2] $end
$var wire 1 F Prescale [1] $end
$var wire 1 G Prescale [0] $end
$var reg 1 h enable $end
$var reg 1 i dat_samp_en $end
$var reg 1 j deser_en $end
$var reg 1 k data_valid $end
$var reg 1 l stp_chk_en $end
$var reg 1 m strt_chk_en $end
$var reg 1 n par_chk_en $end
$var reg 3 o current_state [2:0] $end
$var reg 3 p next_state [2:0] $end
$upscope $end
$upscope $end
$upscope $end

$scope begin std $end
$upscope $end
$enddefinitions $end
#0
$dumpvars
0"
1#
1$
1%
0&
0'
b1000 (
xZ
0[
0\
0]
bx _
bx `
bx a
b0 b
xd
xf
0g
0h
1i
0j
0k
0l
0m
0n
b0 o
b0 p
bx 5
x6
bx 7
bx 8
bx 9
bx :
bx ;
b10000111101000 !
b1000 <
b1000 ^
b1000 c
bx 4
0)
x*
x+
x3
x2
x1
x0
x/
x.
x-
x,
0H
0I
0J
0K
0L
0M
1N
xO
xU
xT
xS
xR
xQ
xP
0Y
0X
0W
0V
xe
0G
0F
0E
1D
0C
0B
0A
0@
1?
1>
1=
$end
#542000
0#
0=
#1084000
1#
1=
#1626000
0#
0=
#2168000
1#
1=
#2710000
0#
0=
#3252000
1#
1=
#3794000
0#
0=
#4336000
1#
1=
#4340000
1"
#4878000
0#
0=
#5420000
1#
1=
#5962000
0#
0=
#6504000
1#
1=
#7046000
0#
0=
#7588000
1#
1=
#8130000
0#
0=
#8672000
1#
1=
#8680000
0$
0"
0>
b0 _
b0 `
b0 a
0d
0f
03
02
01
00
0/
0.
0-
0,
0e
0U
0T
0S
0R
0Q
0P
0*
0+
0i
1i
#9214000
0#
0=
#9756000
1#
1=
#10298000
0#
0=
#10840000
1#
1=
#11382000
0#
0=
#11924000
1#
1=
#12466000
0#
0=
#13008000
1#
1=
#13020000
1"
#13550000
0#
0=
#14092000
1#
1=
#14634000
0#
0=
#15176000
1#
1=
#15718000
0#
0=
#16260000
1#
1=
#16802000
0#
0=
#17344000
1#
1=
#17360000
1$
b1101001010 9
b1000 :
b10100101 ;
b0 4
0%
0"
1>
0?
b1 p
0i
1i
1h
1H
#17886000
0#
0=
#18428000
1#
1=
b1 a
b1 o
1U
0h
0i
1i
1h
#18970000
0#
0=
#19512000
1#
1=
b10 a
0U
1T
0h
0i
1i
1h
#20054000
0#
0=
#20596000
1#
1=
b11 a
1U
0h
0i
1i
1h
#21138000
0#
0=
#21680000
1#
1=
b100 a
0U
0T
1S
0h
0i
1i
1h
#21700000
1"
#22222000
0#
0=
#22764000
1#
1=
b101 a
1U
0h
0i
1i
1h
#23306000
0#
0=
#23848000
1#
1=
b110 a
0U
1T
0h
0i
1i
1h
#24390000
0#
0=
#24932000
1#
1=
0Z
b111 a
0O
1U
0h
0i
1i
1h
1m
1J
#25474000
0#
0=
#26016000
1#
1=
b0 a
b1 b
1Y
0U
0T
0S
0h
0i
0m
1i
1h
b10 p
0J
#26040000
b1 4
1%
0"
1?
0h
0i
1i
1h
#26558000
0#
0=
#27100000
1#
1=
b10 o
b1 a
1U
0h
0i
1i
1h
#27642000
0#
0=
#28184000
1#
1=
b10 a
0U
1T
0h
0i
1i
1h
#28726000
0#
0=
#29268000
1#
1=
b11 a
1U
0h
0i
1i
1h
#29810000
0#
0=
#30352000
1#
1=
1[
b100 a
0U
0T
1S
0h
0i
1i
1h
#30380000
1"
#30894000
0#
0=
#31436000
1#
1=
b101 a
1\
1U
0h
0i
1i
1h
#31978000
0#
0=
#32520000
1#
1=
1]
b110 a
0U
1T
0h
0i
1i
1h
#33062000
0#
0=
#33604000
1#
1=
b111 a
1Z
1O
1U
0h
0i
1i
1h
1j
1M
#34146000
0#
0=
#34688000
1#
1=
b1 _
b1 `
0[
0\
0]
b0 a
b10 b
13
1e
0Y
1X
0U
0T
0S
0h
0i
0j
1i
1h
0M
#34720000
b10 4
0%
0"
0?
0h
0i
1i
1h
#35230000
0#
0=
#35772000
1#
1=
b1 a
1U
0h
0i
1i
1h
#36314000
0#
0=
#36856000
1#
1=
b10 a
0U
1T
0h
0i
1i
1h
#37398000
0#
0=
#37940000
1#
1=
b11 a
1U
0h
0i
1i
1h
#38482000
0#
0=
#39024000
1#
1=
b100 a
0U
0T
1S
0h
0i
1i
1h
#39060000
1"
#39566000
0#
0=
#40108000
1#
1=
b101 a
1U
0h
0i
1i
1h
#40650000
0#
0=
#41192000
1#
1=
b110 a
0U
1T
0h
0i
1i
1h
#41734000
0#
0=
#42276000
1#
1=
0Z
b111 a
0O
1U
0h
0i
1i
1h
1j
1M
#42818000
0#
0=
#43360000
1#
1=
b10 `
b0 a
b11 b
1Y
0U
0T
0S
0h
0i
0j
1i
1h
0M
#43400000
b11 4
1%
0"
1?
0h
0i
1i
1h
#43902000
0#
0=
#44444000
1#
1=
b1 a
1U
0h
0i
1i
1h
#44986000
0#
0=
#45528000
1#
1=
b10 a
0U
1T
0h
0i
1i
1h
#46070000
0#
0=
#46612000
1#
1=
b11 a
1U
0h
0i
1i
1h
#47154000
0#
0=
#47696000
1#
1=
1[
b100 a
0U
0T
1S
0h
0i
1i
1h
#47740000
1"
#48238000
0#
0=
#48780000
1#
1=
b101 a
1\
1U
0h
0i
1i
1h
#49322000
0#
0=
#49864000
1#
1=
1]
b110 a
0U
1T
0h
0i
1i
1h
#50406000
0#
0=
#50948000
1#
1=
b111 a
1Z
1O
1U
0h
0i
1i
1h
1j
1M
#51490000
0#
0=
#52032000
1#
1=
b101 _
b11 `
0[
0\
0]
b0 a
b100 b
11
0e
0Y
0X
1W
0U
0T
0S
0h
0i
0j
1i
1h
0M
#52080000
b100 4
0%
0"
0?
0h
0i
1i
1h
#52574000
0#
0=
#53116000
1#
1=
b1 a
1U
0h
0i
1i
1h
#53658000
0#
0=
#54200000
1#
1=
b10 a
0U
1T
0h
0i
1i
1h
#54742000
0#
0=
#55284000
1#
1=
b11 a
1U
0h
0i
1i
1h
#55826000
0#
0=
#56368000
1#
1=
b100 a
0U
0T
1S
0h
0i
1i
1h
#56420000
1"
#56910000
0#
0=
#57452000
1#
1=
b101 a
1U
0h
0i
1i
1h
#57994000
0#
0=
#58536000
1#
1=
b110 a
0U
1T
0h
0i
1i
1h
#59078000
0#
0=
#59620000
1#
1=
0Z
b111 a
0O
1U
0h
0i
1i
1h
1j
1M
#60162000
0#
0=
#60704000
1#
1=
b100 `
b0 a
b101 b
1Y
0U
0T
0S
0h
0i
0j
1i
1h
0M
#60760000
b101 4
0"
#61246000
0#
0=
#61788000
1#
1=
b1 a
1U
0h
0i
1i
1h
#62330000
0#
0=
#62872000
1#
1=
b10 a
0U
1T
0h
0i
1i
1h
#63414000
0#
0=
#63956000
1#
1=
b11 a
1U
0h
0i
1i
1h
#64498000
0#
0=
#65040000
1#
1=
b100 a
0U
0T
1S
0h
0i
1i
1h
#65100000
1"
#65582000
0#
0=
#66124000
1#
1=
b101 a
1U
0h
0i
1i
1h
#66666000
0#
0=
#67208000
1#
1=
b110 a
0U
1T
0h
0i
1i
1h
#67750000
0#
0=
#68292000
1#
1=
b111 a
1U
0h
0i
1i
1h
1j
1M
#68834000
0#
0=
